luqum/__init__.py
luqum/auto_head_tail.py
luqum/check.py
luqum/deprecated_utils.py
luqum/exceptions.py
luqum/head_tail.py
luqum/naming.py
luqum/parser.py
luqum/parsetab.py
luqum/pretty.py
luqum/thread.py
luqum/tree.py
luqum/utils.py
luqum/visitor.py
luqum/elasticsearch/__init__.py
luqum/elasticsearch/nested.py
luqum/elasticsearch/schema.py
luqum/elasticsearch/tree.py
luqum/elasticsearch/visitor.py
luqum-0.13.0.dist-info/LICENSE
luqum-0.13.0.dist-info/LICENSE.Apache2
luqum-0.13.0.dist-info/LICENSE.LGPLv3
luqum-0.13.0.dist-info/METADATA
luqum-0.13.0.dist-info/WHEEL
luqum-0.13.0.dist-info/top_level.txt
luqum-0.13.0.dist-info/RECORD
